{
  "metadata": {
    "id": "891863",
    "arquivo": "891863 - Notificação de OC Grave para clientes Diamante.docx",
    "caminho": "C:\\Users\\lcruz\\Belgo BBP\\Tester\\extracted_tests\\Testes - Belgo Arames\\891863 - Notificação de OC Grave para clientes Diamante.docx",
    "tamanho_bytes": 674218,
    "data_modificacao": "2025-11-14T18:05:20",
    "extraido_em": "2026-01-13T11:31:15.060291",
    "status": "extraido",
    "total_paragrafos": 6,
    "total_tabelas": 1
  },
  "conteudo": {
    "paragrafos": [
      "Ordem de venda",
      "É possível selecionar várias notas fiscais simultaneamente para abrir a OC",
      "Tela de Ocorrência no HUB de Gestão de OCs exibindo múltiplas Notas Fiscais vinculadas:",
      "O nível Diamante Grave deverá receber o e-mail conforme regra prevista",
      "E-mail recebido e tratativa concluída. O sistema deve enviar apenas um e-mail caso o usuário esteja vinculado a outro grupo",
      "E-mail recebido com sucesso: "
    ],
    "tabelas": [
      [
        [
          "",
          "Documento\n891863 - Notificação de OC Grave para clientes Diamante",
          "Data de Criação\n14/11/2025"
        ],
        [
          "",
          "Projeto\nGO WIRE",
          "Projeto\nGO WIRE"
        ]
      ]
    ],
    "total_paragrafos": 6,
    "total_tabelas": 1
  }
}